{
  "name": "ProMarker CLI Development",
  "dockerFile": "Dockerfile",
  "customizations": {
    "vscode": {
      "settings": {
        "terminal.integrated.defaultProfile.linux": "bash",
        "editor.formatOnSave": true,
        "editor.codeActionsOnSave": {
          "source.fixAll.eslint": "explicit"
        },
        "typescript.preferences.importModuleSpecifier": "relative",
        "typescript.suggest.autoImports": true,
        "files.exclude": {
          "**/node_modules": true,
          "**/dist": true,
          "**/.git": true
        }
      },
      "extensions": [
        "ms-vscode.vscode-typescript-next",
        "esbenp.prettier-vscode",
        "dbaeumer.vscode-eslint",
        "ms-vscode.vscode-json",
        "redhat.vscode-yaml",
        "GitHub.copilot",
        "GitHub.copilot-chat",
        "ms-vscode.test-adapter-converter",
        "zxh404.vscode-proto3"
      ]
    }
  },
  "postCreateCommand": "npm install",
  "postStartCommand": "npm run build",
  "forwardPorts": [],
  "features": {
    "ghcr.io/devcontainers/features/node:1": {
      "version": "18"
    },
    "ghcr.io/devcontainers/features/git:1": {
      "ppa": true,
      "version": "latest"
    },
    "ghcr.io/devcontainers/features/github-cli:1": {
      "version": "latest"
    }
  },
  "remoteUser": "node"
}